{
  "kind": "collectionType",
  "collectionName": "blog_posts",
  "info": {
    "singularName": "blog-post",
    "pluralName": "blog-posts",
    "displayName": "Zafira-blog"
  },
  "options": {
    "draftAndPublish": true
  },
  "pluginOptions": {},
  "attributes": {
    "title": {
      "type": "string"
    },
    "textBody": {
      "type": "blocks"
    },
    "author": {
      "type": "string"
    },
    "externalId": {
      "type": "string"
    },
    "synced": {
      "type": "boolean"
    },
    "photo": {
      "type": "media",
      "multiple": false,
      "allowedTypes": [
        "images",
        "files"
      ]
    }
  }
}
